bitdust/__init__.py
bitdust/bitdust.py
bitdust/bpworker.py
bitdust/CodernityDB/__init__.py
bitdust/CodernityDB/database.py
bitdust/CodernityDB/database_gevent.py
bitdust/CodernityDB/database_safe_shared.py
bitdust/CodernityDB/database_super_thread_safe.py
bitdust/CodernityDB/database_thread_safe.py
bitdust/CodernityDB/debug_stuff.py
bitdust/CodernityDB/env.py
bitdust/CodernityDB/hash_index.py
bitdust/CodernityDB/index.py
bitdust/CodernityDB/indexcreator.py
bitdust/CodernityDB/lfu_cache.py
bitdust/CodernityDB/lfu_cache_with_lock.py
bitdust/CodernityDB/migrate.py
bitdust/CodernityDB/misc.py
bitdust/CodernityDB/patch.py
bitdust/CodernityDB/rr_cache.py
bitdust/CodernityDB/rr_cache_with_lock.py
bitdust/CodernityDB/sharded_hash.py
bitdust/CodernityDB/sharded_index.py
bitdust/CodernityDB/storage.py
bitdust/CodernityDB/tree_index.py
bitdust/CodernityDB3/__init__.py
bitdust/CodernityDB3/database.py
bitdust/CodernityDB3/database_gevent.py
bitdust/CodernityDB3/database_safe_shared.py
bitdust/CodernityDB3/database_super_thread_safe.py
bitdust/CodernityDB3/database_thread_safe.py
bitdust/CodernityDB3/debug_stuff.py
bitdust/CodernityDB3/env.py
bitdust/CodernityDB3/hash_index.py
bitdust/CodernityDB3/index.py
bitdust/CodernityDB3/indexcreator.py
bitdust/CodernityDB3/lfu_cache.py
bitdust/CodernityDB3/lfu_cache_with_lock.py
bitdust/CodernityDB3/migrate.py
bitdust/CodernityDB3/misc.py
bitdust/CodernityDB3/patch.py
bitdust/CodernityDB3/rr_cache.py
bitdust/CodernityDB3/rr_cache_with_lock.py
bitdust/CodernityDB3/sharded_hash.py
bitdust/CodernityDB3/sharded_index.py
bitdust/CodernityDB3/storage.py
bitdust/CodernityDB3/tree_index.py
bitdust/access/__init__.py
bitdust/access/group_access_donor.py
bitdust/access/group_member.py
bitdust/access/groups.py
bitdust/access/key_ring.py
bitdust/access/shared_access_coordinator.py
bitdust/access/shared_access_donor.py
bitdust/automats/__init__.py
bitdust/automats/automat.py
bitdust/automats/global_state.py
bitdust/blockchain/__init__.py
bitdust_p2p-0.0.3.dist-info/LICENSE.txt
bitdust_p2p-0.0.3.dist-info/METADATA
bitdust_p2p-0.0.3.dist-info/WHEEL
bitdust_p2p-0.0.3.dist-info/top_level.txt
bitdust_p2p-0.0.3.dist-info/RECORD
