Metadata-Version: 2.1
Name: bitdust-p2p
Version: 0.0.3
Summary: BitDust is new software framework to build distributed and secure peer-to-peer applications.
Home-page: https://github.com/bitdust-io/public.git
Author: Veselin Penev
Author-email: bitdust.io@gmail.com
License: GNU Affero General Public License v3 or later (AGPLv3+)
Platform: UNKNOWN
Classifier: Development Status :: 3 - Alpha
Classifier: Environment :: Console
Classifier: Environment :: No Input/Output (Daemon)
Classifier: Framework :: Twisted
Classifier: Intended Audience :: Developers
Classifier: Intended Audience :: End Users/Desktop
Classifier: Intended Audience :: Information Technology
Classifier: Intended Audience :: Science/Research
Classifier: Intended Audience :: Telecommunications Industry
Classifier: License :: OSI Approved :: GNU Affero General Public License v3 or later (AGPLv3+)
Classifier: Natural Language :: English
Classifier: Operating System :: OS Independent
Classifier: Programming Language :: Python
Classifier: Programming Language :: Python :: 2
Classifier: Programming Language :: Python :: 2.7
Classifier: Programming Language :: Python :: 3
Classifier: Programming Language :: Python :: 3.6
Classifier: Topic :: Communications :: Chat
Classifier: Topic :: Internet :: WWW/HTTP
Classifier: Topic :: Communications :: File Sharing
Classifier: Topic :: Desktop Environment :: File Managers
Classifier: Topic :: Internet :: File Transfer Protocol (FTP)
Classifier: Topic :: Security :: Cryptography
Classifier: Topic :: System :: Archiving :: Backup
Classifier: Topic :: System :: Distributed Computing
Classifier: Topic :: System :: Filesystems
Classifier: Topic :: System :: System Shells
Classifier: Topic :: Utilities
Requires-Dist: appdirs (==1.4.3)
Requires-Dist: attrs (==19.3.0)
Requires-Dist: Automat (==0.8.0)
Requires-Dist: cffi (==1.13.2)
Requires-Dist: constantly (==15.1.0)
Requires-Dist: cryptography (==2.8)
Requires-Dist: distlib (==0.3.0)
Requires-Dist: filelock (==3.0.12)
Requires-Dist: hyperlink (==19.0.0)
Requires-Dist: idna (==2.8)
Requires-Dist: incremental (==17.5.0)
Requires-Dist: psutil (==5.6.7)
Requires-Dist: pyasn1 (==0.4.8)
Requires-Dist: pyasn1-modules (==0.2.7)
Requires-Dist: pycparser (==2.19)
Requires-Dist: pycryptodomex (==3.9.4)
Requires-Dist: PyHamcrest (==1.9.0)
Requires-Dist: pyparsing (==2.4.6)
Requires-Dist: service-identity (==18.1.0)
Requires-Dist: six (==1.13.0)
Requires-Dist: zope.interface (==4.7.1)
Requires-Dist: virtualenv (==20.0.21)
Requires-Dist: Twisted (==20.3.0)
